dibug/__init__.py
dibug/abc.py
dibug/commands/__init__.py
dibug/commands/eval.py
dibug/commands/info.py
dibug/commands/kill.py
dibug/commands/shell.py
dibug/dibugger.py
dibug/py.typed
dibug/utils/__init__.py
dibug/utils/chunk.py
dibug/utils/embed.py
dibug/utils/object.py
dibug/version.py
dibug-0.5.1.dist-info/LICENSE
dibug-0.5.1.dist-info/METADATA
dibug-0.5.1.dist-info/WHEEL
dibug-0.5.1.dist-info/RECORD
