Metadata-Version: 2.1
Name: dibug
Version: 0.5.1
Summary: Debugging Tool for discord.py
Home-page: https://github.com/star0202/dibug
License: MIT
Author: Starcea
Author-email: stardev.uwu@gmail.com
Requires-Python: >=3.10,<4.0
Classifier: License :: OSI Approved :: MIT License
Classifier: Programming Language :: Python :: 3
Classifier: Programming Language :: Python :: 3.10
Classifier: Programming Language :: Python :: 3.11
Requires-Dist: async-eval (>=0.1.11,<0.2.0)
Requires-Dist: discord-py (>=2.0.0)
Requires-Dist: psutil (>=5.9.5,<6.0.0)
Project-URL: Repository, https://github.com/star0202/dibug
